setup.py
awsmldistributionsjb/Binomialdistribution.py
awsmldistributionsjb/Gaussiandistribution.py
awsmldistributionsjb/Generaldistribution.py
awsmldistributionsjb/__init__.py
awsmldistributionsjb.egg-info/PKG-INFO
awsmldistributionsjb.egg-info/SOURCES.txt
awsmldistributionsjb.egg-info/dependency_links.txt
awsmldistributionsjb.egg-info/not-zip-safe
awsmldistributionsjb.egg-info/top_level.txt