Metadata-Version: 1.0
Name: awsmldistributionsjb
Version: 0.2
Summary: Gaussian and Binomial distributions
Home-page: UNKNOWN
Author: Joseph Berchmans
Author-email: UNKNOWN
License: UNKNOWN
Platform: UNKNOWN
